cssselect2/__init__.py
cssselect2/_compat.py
cssselect2/_version.py
cssselect2/compiler.py
cssselect2/ext_utils.py
cssselect2/extensions.py
cssselect2/parser.py
cssselect2/tree.py
cssselect2/tests/LICENSE
cssselect2/tests/__init__.py
cssselect2/tests/content.xhtml
cssselect2/tests/ids.html
cssselect2/tests/invalid_selectors.json
cssselect2/tests/make_valid_selectors_json.sh
cssselect2/tests/shakespeare.html
cssselect2/tests/test_cssselect2.py
cssselect2/tests/valid_selectors.json
cnx_cssselect2-0.2.3.dist-info/LICENSE
cnx_cssselect2-0.2.3.dist-info/METADATA
cnx_cssselect2-0.2.3.dist-info/WHEEL
cnx_cssselect2-0.2.3.dist-info/top_level.txt
cnx_cssselect2-0.2.3.dist-info/RECORD
