Metadata-Version: 2.1
Name: cnx-cssselect2
Version: 0.2.3
Summary: CSS selectors for Python ElementTree
Home-page: https://github.com/connexions/cnx-cssselect2
Author: OpenStax CNX
Author-email: info@cnx.org
License: BSD
Platform: UNKNOWN
Requires-Dist: tinycss2
Provides-Extra: test
Requires-Dist: pytest-runner; extra == 'test'
Requires-Dist: pytest-cov; extra == 'test'
Requires-Dist: pytest-flake8; extra == 'test'
Requires-Dist: pytest-isort; extra == 'test'
